MANIFEST.in
README.rst
setup.py
AthenaVoice.egg-info/PKG-INFO
AthenaVoice.egg-info/SOURCES.txt
AthenaVoice.egg-info/dependency_links.txt
AthenaVoice.egg-info/requires.txt
AthenaVoice.egg-info/top_level.txt
athena/__init__.py
athena/__main__.py
athena/brain.py
athena/config.py
athena/settings.py
athena/stt.py
athena/tts.py
athena/classes/__init__.py
athena/classes/module.py
athena/classes/task.py
athena/media/double-beep.mp3
athena/media/godj.mp3
athena/models/en-us/cmudict-en-us.dict
athena/models/en-us/en-us.lm.dmp
athena/models/en-us/en-us/README
athena/models/en-us/en-us/feat.params
athena/models/en-us/en-us/mdef
athena/models/en-us/en-us/means
athena/models/en-us/en-us/noisedict
athena/models/en-us/en-us/sendump
athena/models/en-us/en-us/transition_matrices
athena/models/en-us/en-us/variances
athena/modules/__init__.py
athena/modules/active/__init__.py
athena/modules/active/bitcoin.py
athena/modules/active/conversation.py
athena/modules/active/emotion.py
athena/modules/active/geo_info.py
athena/modules/active/google.py
athena/modules/active/music.py
athena/modules/active/spotify.py
athena/modules/active/voice_browse.py
athena/modules/active/weather.py
athena/modules/active/wolfram.py
athena/modules/api_library/__init__.py
athena/modules/api_library/bitcoin_api.py
athena/modules/api_library/geo_info_api.py
athena/modules/api_library/spotify_api.py
athena/modules/api_library/true_random_api.py
athena/modules/api_library/user_api.py
athena/modules/api_library/voice_browse_api.py
athena/modules/api_library/weather_api.py
athena/modules/passive/__init__.py
athena/tests/__init__.py
athena/tests/dependencies_test.py
athena/tests/mic_test.py