Metadata-Version: 1.1
Name: AthenaVoice
Version: 1.0.0b1
Summary: Your personal voice assistant
Home-page: https://github.com/athena-voice/athena-voice-client
Author: Athena Voice
Author-email: rcbyron3@gmail.com
License: GPLv3
Keywords: athena voice assistant development
Platform: UNKNOWN
Classifier: Development Status :: 3 - Alpha
Classifier: Intended Audience :: Developers
Classifier: Topic :: Software Development :: Build Tools
Classifier: Topic :: Scientific/Engineering :: Human Machine Interfaces
Classifier: License :: OSI Approved :: GNU General Public License v3 (GPLv3)
Classifier: Programming Language :: Python :: 3
Classifier: Programming Language :: Python :: 3.4
